{
	"partitions" : [
		{
			"name" : "Top",
			"pins" : [
				{
					"name" : "BusMuxOut[0]",
					"strict" : false
				},
				{
					"name" : "BusMuxOut[1]",
					"strict" : false
				},
				{
					"name" : "BusMuxOut[2]",
					"strict" : false
				},
				{
					"name" : "BusMuxOut[3]",
					"strict" : false
				},
				{
					"name" : "BusMuxOut[4]",
					"strict" : false
				},
				{
					"name" : "BusMuxOut[5]",
					"strict" : false
				},
				{
					"name" : "BusMuxOut[6]",
					"strict" : false
				},
				{
					"name" : "BusMuxOut[7]",
					"strict" : false
				},
				{
					"name" : "BusMuxOut[8]",
					"strict" : false
				},
				{
					"name" : "BusMuxOut[9]",
					"strict" : false
				},
				{
					"name" : "BusMuxOut[10]",
					"strict" : false
				},
				{
					"name" : "BusMuxOut[11]",
					"strict" : false
				},
				{
					"name" : "BusMuxOut[12]",
					"strict" : false
				},
				{
					"name" : "BusMuxOut[13]",
					"strict" : false
				},
				{
					"name" : "BusMuxOut[14]",
					"strict" : false
				},
				{
					"name" : "BusMuxOut[15]",
					"strict" : false
				},
				{
					"name" : "BusMuxOut[16]",
					"strict" : false
				},
				{
					"name" : "BusMuxOut[17]",
					"strict" : false
				},
				{
					"name" : "BusMuxOut[18]",
					"strict" : false
				},
				{
					"name" : "BusMuxOut[19]",
					"strict" : false
				},
				{
					"name" : "BusMuxOut[20]",
					"strict" : false
				},
				{
					"name" : "BusMuxOut[21]",
					"strict" : false
				},
				{
					"name" : "BusMuxOut[22]",
					"strict" : false
				},
				{
					"name" : "BusMuxOut[23]",
					"strict" : false
				},
				{
					"name" : "BusMuxOut[24]",
					"strict" : false
				},
				{
					"name" : "BusMuxOut[25]",
					"strict" : false
				},
				{
					"name" : "BusMuxOut[26]",
					"strict" : false
				},
				{
					"name" : "BusMuxOut[27]",
					"strict" : false
				},
				{
					"name" : "BusMuxOut[28]",
					"strict" : false
				},
				{
					"name" : "BusMuxOut[29]",
					"strict" : false
				},
				{
					"name" : "BusMuxOut[30]",
					"strict" : false
				},
				{
					"name" : "BusMuxOut[31]",
					"strict" : false
				},
				{
					"name" : "ALUResult[0]",
					"strict" : false
				},
				{
					"name" : "ALUResult[1]",
					"strict" : false
				},
				{
					"name" : "ALUResult[2]",
					"strict" : false
				},
				{
					"name" : "ALUResult[3]",
					"strict" : false
				},
				{
					"name" : "ALUResult[4]",
					"strict" : false
				},
				{
					"name" : "ALUResult[5]",
					"strict" : false
				},
				{
					"name" : "ALUResult[6]",
					"strict" : false
				},
				{
					"name" : "ALUResult[7]",
					"strict" : false
				},
				{
					"name" : "ALUResult[8]",
					"strict" : false
				},
				{
					"name" : "ALUResult[9]",
					"strict" : false
				},
				{
					"name" : "ALUResult[10]",
					"strict" : false
				},
				{
					"name" : "ALUResult[11]",
					"strict" : false
				},
				{
					"name" : "ALUResult[12]",
					"strict" : false
				},
				{
					"name" : "ALUResult[13]",
					"strict" : false
				},
				{
					"name" : "ALUResult[14]",
					"strict" : false
				},
				{
					"name" : "ALUResult[15]",
					"strict" : false
				},
				{
					"name" : "ALUResult[16]",
					"strict" : false
				},
				{
					"name" : "ALUResult[17]",
					"strict" : false
				},
				{
					"name" : "ALUResult[18]",
					"strict" : false
				},
				{
					"name" : "ALUResult[19]",
					"strict" : false
				},
				{
					"name" : "ALUResult[20]",
					"strict" : false
				},
				{
					"name" : "ALUResult[21]",
					"strict" : false
				},
				{
					"name" : "ALUResult[22]",
					"strict" : false
				},
				{
					"name" : "ALUResult[23]",
					"strict" : false
				},
				{
					"name" : "ALUResult[24]",
					"strict" : false
				},
				{
					"name" : "ALUResult[25]",
					"strict" : false
				},
				{
					"name" : "ALUResult[26]",
					"strict" : false
				},
				{
					"name" : "ALUResult[27]",
					"strict" : false
				},
				{
					"name" : "ALUResult[28]",
					"strict" : false
				},
				{
					"name" : "ALUResult[29]",
					"strict" : false
				},
				{
					"name" : "ALUResult[30]",
					"strict" : false
				},
				{
					"name" : "ALUResult[31]",
					"strict" : false
				},
				{
					"name" : "A[0]",
					"strict" : false
				},
				{
					"name" : "B[0]",
					"strict" : false
				},
				{
					"name" : "Op[3]",
					"strict" : false
				},
				{
					"name" : "Op[2]",
					"strict" : false
				},
				{
					"name" : "Op[0]",
					"strict" : false
				},
				{
					"name" : "Op[1]",
					"strict" : false
				},
				{
					"name" : "A[1]",
					"strict" : false
				},
				{
					"name" : "B[1]",
					"strict" : false
				},
				{
					"name" : "A[2]",
					"strict" : false
				},
				{
					"name" : "B[2]",
					"strict" : false
				},
				{
					"name" : "A[3]",
					"strict" : false
				},
				{
					"name" : "B[3]",
					"strict" : false
				},
				{
					"name" : "A[4]",
					"strict" : false
				},
				{
					"name" : "B[4]",
					"strict" : false
				},
				{
					"name" : "A[5]",
					"strict" : false
				},
				{
					"name" : "B[5]",
					"strict" : false
				},
				{
					"name" : "A[6]",
					"strict" : false
				},
				{
					"name" : "B[6]",
					"strict" : false
				},
				{
					"name" : "A[7]",
					"strict" : false
				},
				{
					"name" : "B[7]",
					"strict" : false
				},
				{
					"name" : "A[8]",
					"strict" : false
				},
				{
					"name" : "B[8]",
					"strict" : false
				},
				{
					"name" : "A[9]",
					"strict" : false
				},
				{
					"name" : "B[9]",
					"strict" : false
				},
				{
					"name" : "A[10]",
					"strict" : false
				},
				{
					"name" : "B[10]",
					"strict" : false
				},
				{
					"name" : "A[11]",
					"strict" : false
				},
				{
					"name" : "B[11]",
					"strict" : false
				},
				{
					"name" : "A[12]",
					"strict" : false
				},
				{
					"name" : "B[12]",
					"strict" : false
				},
				{
					"name" : "A[13]",
					"strict" : false
				},
				{
					"name" : "B[13]",
					"strict" : false
				},
				{
					"name" : "A[14]",
					"strict" : false
				},
				{
					"name" : "B[14]",
					"strict" : false
				},
				{
					"name" : "A[15]",
					"strict" : false
				},
				{
					"name" : "B[15]",
					"strict" : false
				},
				{
					"name" : "A[16]",
					"strict" : false
				},
				{
					"name" : "B[16]",
					"strict" : false
				},
				{
					"name" : "B[17]",
					"strict" : false
				},
				{
					"name" : "A[17]",
					"strict" : false
				},
				{
					"name" : "B[18]",
					"strict" : false
				},
				{
					"name" : "A[18]",
					"strict" : false
				},
				{
					"name" : "B[19]",
					"strict" : false
				},
				{
					"name" : "A[19]",
					"strict" : false
				},
				{
					"name" : "B[20]",
					"strict" : false
				},
				{
					"name" : "A[20]",
					"strict" : false
				},
				{
					"name" : "B[21]",
					"strict" : false
				},
				{
					"name" : "A[21]",
					"strict" : false
				},
				{
					"name" : "B[22]",
					"strict" : false
				},
				{
					"name" : "A[22]",
					"strict" : false
				},
				{
					"name" : "B[23]",
					"strict" : false
				},
				{
					"name" : "A[23]",
					"strict" : false
				},
				{
					"name" : "B[24]",
					"strict" : false
				},
				{
					"name" : "A[24]",
					"strict" : false
				},
				{
					"name" : "B[25]",
					"strict" : false
				},
				{
					"name" : "A[25]",
					"strict" : false
				},
				{
					"name" : "B[26]",
					"strict" : false
				},
				{
					"name" : "A[26]",
					"strict" : false
				},
				{
					"name" : "B[27]",
					"strict" : false
				},
				{
					"name" : "A[27]",
					"strict" : false
				},
				{
					"name" : "B[28]",
					"strict" : false
				},
				{
					"name" : "A[28]",
					"strict" : false
				},
				{
					"name" : "B[29]",
					"strict" : false
				},
				{
					"name" : "A[29]",
					"strict" : false
				},
				{
					"name" : "B[30]",
					"strict" : false
				},
				{
					"name" : "A[30]",
					"strict" : false
				},
				{
					"name" : "B[31]",
					"strict" : false
				},
				{
					"name" : "A[31]",
					"strict" : false
				},
				{
					"name" : "RZout",
					"strict" : false
				},
				{
					"name" : "RAout",
					"strict" : false
				},
				{
					"name" : "RBout",
					"strict" : false
				},
				{
					"name" : "clock",
					"strict" : false
				},
				{
					"name" : "clear",
					"strict" : false
				},
				{
					"name" : "RZin",
					"strict" : false
				},
				{
					"name" : "RAin",
					"strict" : false
				},
				{
					"name" : "RBin",
					"strict" : false
				}
			]
		}
	]
}